concataudio/README.MD
concataudio/__init__.py
concataudio/requirements.txt
concataudio/thirdparty.json
concataudio-0.10.dist-info/LICENSE.rst
concataudio-0.10.dist-info/METADATA
concataudio-0.10.dist-info/WHEEL
concataudio-0.10.dist-info/top_level.txt
concataudio-0.10.dist-info/RECORD
