Metadata-Version: 2.1
Name: concataudio
Version: 0.10
Summary: Concatenates multiple audio files from the given list and exports the result.
Home-page: https://github.com/hansalemaos/concataudio
Author: Johannes Fischer
Author-email: aulasparticularesdealemaosp@gmail.com
License: MIT
Keywords: wav,Concatenate
Classifier: Development Status :: 4 - Beta
Classifier: Programming Language :: Python :: 3 :: Only
Classifier: Programming Language :: Python :: 3.10
Classifier: Topic :: Software Development :: Libraries :: Python Modules
Classifier: Topic :: Utilities
License-File: LICENSE.rst
Requires-Dist: pydub
